{
  "openapi": "3.0.1",
  "info": {
    "title": "Api",
    "version": "v1"
  },
  "paths": {
    "/api/v1/Sample/list": {
      "get": {
        "tags": [
          "Sample"
        ],
        "operationId": "List",
        "responses": {
          "200": {
            "description": "Success",
            "content": {
              "text/plain": {
                "schema": {
                  "type": "array",
                  "items": {
                    "type": "string"
                  }
                }
              },
              "application/json": {
                "schema": {
                  "type": "array",
                  "items": {
                    "type": "string"
                  }
                }
              },
              "text/json": {
                "schema": {
                  "type": "array",
                  "items": {
                    "type": "string"
                  }
                }
              }
            }
          },
          "500": {
            "description": "Server Error",
            "content": {
              "text/plain": {
                "schema": { }
              },
              "application/json": {
                "schema": { }
              },
              "text/json": {
                "schema": { }
              }
            }
          }
        }
      }
    },
    "/api/v1/Sample/get/{id}": {
      "get": {
        "tags": [
          "Sample"
        ],
        "operationId": "Get",
        "parameters": [
          {
            "name": "id",
            "in": "path",
            "required": true,
            "schema": {
              "type": "string"
            }
          },
          {
            "name": "number",
            "in": "query",
            "schema": {
              "type": "integer",
              "format": "int32"
            }
          }
        ],
        "responses": {
          "200": {
            "description": "Success",
            "content": {
              "text/plain": {
                "schema": {
                  "$ref": "#/components/schemas/GetSampleViewModel"
                }
              },
              "application/json": {
                "schema": {
                  "$ref": "#/components/schemas/GetSampleViewModel"
                }
              },
              "text/json": {
                "schema": {
                  "$ref": "#/components/schemas/GetSampleViewModel"
                }
              }
            }
          },
          "400": {
            "description": "Bad Request",
            "content": {
              "text/plain": {
                "schema": { }
              },
              "application/json": {
                "schema": { }
              },
              "text/json": {
                "schema": { }
              }
            }
          },
          "500": {
            "description": "Server Error",
            "content": {
              "text/plain": {
                "schema": { }
              },
              "application/json": {
                "schema": { }
              },
              "text/json": {
                "schema": { }
              }
            }
          }
        }
      }
    },
    "/api/v1/Sample/upsert": {
      "post": {
        "tags": [
          "Sample"
        ],
        "operationId": "Upsert",
        "requestBody": {
          "content": {
            "application/json": {
              "schema": {
                "$ref": "#/components/schemas/CreateSample"
              }
            },
            "text/json": {
              "schema": {
                "$ref": "#/components/schemas/CreateSample"
              }
            },
            "application/*+json": {
              "schema": {
                "$ref": "#/components/schemas/CreateSample"
              }
            }
          }
        },
        "responses": {
          "202": {
            "description": "Accepted"
          },
          "400": {
            "description": "Bad Request",
            "content": {
              "text/plain": {
                "schema": { }
              },
              "application/json": {
                "schema": { }
              },
              "text/json": {
                "schema": { }
              }
            }
          },
          "500": {
            "description": "Server Error",
            "content": {
              "text/plain": {
                "schema": { }
              },
              "application/json": {
                "schema": { }
              },
              "text/json": {
                "schema": { }
              }
            }
          }
        }
      }
    }
  },
  "components": {
    "schemas": {
      "CreateSample": {
        "type": "object",
        "properties": {
          "name": {
            "type": "string",
            "nullable": true
          }
        },
        "additionalProperties": false
      },
      "GetSampleViewModel": {
        "type": "object",
        "properties": {
          "id": {
            "type": "string",
            "nullable": true
          },
          "name": {
            "type": "string",
            "nullable": true
          },
          "createdAt": {
            "type": "string",
            "format": "date-time"
          },
          "updatedAt": {
            "type": "string",
            "format": "date-time"
          }
        },
        "additionalProperties": false
      }
    }
  }
}